verilog_cpu/reg.sv
module Reg #(parameter WIDTH = 4) (
  output [WIDTH-1:0] d_out,
  input wire [WIDTH-1:0] data,
  input wire clk,
  input wire we, // Write enable
  input wire rst
);

  reg [WIDTH-1:0] stored_data;

  always @(posedge clk) begin
    if (rst) begin
      stored_data <= 4'b0000;
    end
    else if (we) begin
      stored_data <= data;
    end
  end

  assign d_out = stored_data;

endmodule

verilog_cpu/reg.tb.sv
module Reg_tb();
    logic clk;
  logic rst;
  logic we;
  logic [3:0] data;
  wire [3:0] d_out;

  // DUT instance
  Reg #(4) dut (
    .d_out(d_out),
    .data(data),
    .clk(clk),
    .we(we),
    .rst(rst)
  );

  // Clock generator (10ns period)
  always #5 clk = ~clk;

  initial begin
    $dumpfile("reg_test.vcd");
    $dumpvars(0, Reg_tb);

    // Initialize
    clk = 0;
    rst = 1;
    we  = 0;
    data = 4'b0000;

    // Reset pulse
    #10 rst = 0;

    // Write 1010
    #10 data = 4'b1010; we = 1;
    #10 we = 0;

    // Wait a bit
    #20;

    // Write 1111
    data = 4'b1111; we = 1;
    #10 we = 0;

    // Reset again
    #10 rst = 1;
    #10 rst = 0;

    #20 $finish;
  end

endmodule

verilog_cpu/reg_test.vcd
$date
	Sun Aug 10 22:09:55 2025
$end
$version
	Icarus Verilog
$end
$timescale
	1s
$end
$scope module Reg_tb $end
$var wire 4 ! d_out [3:0] $end
$var reg 1 " clk $end
$var reg 4 # data [3:0] $end
$var reg 1 $ rst $end
$var reg 1 % we $end
$scope module dut $end
$var wire 1 " clk $end
$var wire 4 & d_out [3:0] $end
$var wire 4 ' data [3:0] $end
$var wire 1 $ rst $end
$var wire 1 % we $end
$var parameter 32 ( WIDTH $end
$var reg 4 ) stored_data [3:0] $end
$upscope $end
$upscope $end
$enddefinitions $end
$comment Show the parameter values. $end
$dumpall
b100 (
$end
#0
$dumpvars
bx )
b0 '
bx &
0%
1$
b0 #
0"
bx !
$end
#5
b0 !
b0 &
b0 )
1"
#10
0"
0$
#15
1"
#20
0"
1%
b1010 #
b1010 '
#25
b1010 !
b1010 &
b1010 )
1"
#30
0"
0%
#35
1"
#40
0"
#45
1"
#50
0"
1%
b1111 #
b1111 '
#55
b1111 !
b1111 &
b1111 )
1"
#60
0"
0%
#65
1"
#70
0"
1$
#75
b0 !
b0 &
b0 )
1"
#80
0"
0$
